README.md
setup.cfg
setup.py
async_rmq/_init_.py
async_rmq/abstract_rmq_consumer.py
async_rmq/abstract_rmq_rpc_server.py
async_rmq/abtract_rmq_rpc_client.py
async_rmq/consumer_threading.py
async_rmq/rmq_functions.py
async_rmq_v.egg-info/PKG-INFO
async_rmq_v.egg-info/SOURCES.txt
async_rmq_v.egg-info/dependency_links.txt
async_rmq_v.egg-info/not-zip-safe
async_rmq_v.egg-info/top_level.txt