Metadata-Version: 2.1
Name: async-rmq-v
Version: 0.3.10
Summary: Module for working with asynchronous RabbitMQ library
Home-page: UNKNOWN
Author-email: lenden.uk@gmail.com
License: UNKNOWN
Platform: UNKNOWN
